mo_collections/__init__.py
mo_collections/array.py
mo_collections/index.py
mo_collections/matrix.py
mo_collections/multiset.py
mo_collections/persistent_queue.py
mo_collections/queue.py
mo_collections/relation.py
mo_collections/unique_index.py
mo_collections-5.678.25061.dist-info/LICENSE
mo_collections-5.678.25061.dist-info/METADATA
mo_collections-5.678.25061.dist-info/WHEEL
mo_collections-5.678.25061.dist-info/top_level.txt
mo_collections-5.678.25061.dist-info/RECORD
